nordea_analytics/__init__.py
nordea_analytics/convention_variable_names.py
nordea_analytics/curve_variable_names.py
nordea_analytics/forecast_names.py
nordea_analytics/instrument_groups.py
nordea_analytics/instrument_variable_names.py
nordea_analytics/key_figure_names.py
nordea_analytics/search_bond_names.py
nordea_analytics/nalib/__init__.py
nordea_analytics/nalib/auth.py
nordea_analytics/nalib/config.yml
nordea_analytics/nalib/config_test.yml
nordea_analytics/nalib/exceptions.py
nordea_analytics/nalib/proxy_finder.py
nordea_analytics/nalib/util.py
nordea_analytics/nalib/value_retriever.py
nordea_analytics/nalib/background_requests/__init__.py
nordea_analytics/nalib/background_requests/core.py
nordea_analytics/nalib/background_requests/open_banking.py
nordea_analytics/nalib/data_retrieval_client/__init__.py
nordea_analytics/nalib/data_retrieval_client/client.py
nordea_analytics/nalib/data_retrieval_client/core.py
nordea_analytics/nalib/data_retrieval_client/validation.py
nordea_analytics/nalib/data_retrieval_client/dto/__init__.py
nordea_analytics/nalib/data_retrieval_client/dto/background.py
nordea_analytics/nalib/data_retrieval_client/dto/bulk_calculation.py
nordea_analytics/nalib/http/__init__.py
nordea_analytics/nalib/http/core.py
nordea_analytics/nalib/http/errors.py
nordea_analytics/nalib/http/models.py
nordea_analytics/nalib/http/open_banking.py
nordea_analytics/nalib/http/server_events.py
nordea_analytics/nalib/live_keyfigures/__init__.py
nordea_analytics/nalib/live_keyfigures/core.py
nordea_analytics/nalib/live_keyfigures/open_banking.py
nordea_analytics/nalib/live_keyfigures/parsing.py
nordea_analytics/nalib/value_retrievers/AvailableInstruments.py
nordea_analytics/nalib/value_retrievers/BenchmarkDefinition.py
nordea_analytics/nalib/value_retrievers/BondFinder.py
nordea_analytics/nalib/value_retrievers/BondKeyFigureCalculator.py
nordea_analytics/nalib/value_retrievers/BondKeyFigureHorizonCalculator.py
nordea_analytics-1.22.5.dist-info/licenses/LICENCE.md
nordea_analytics-1.22.5.dist-info/METADATA
nordea_analytics-1.22.5.dist-info/WHEEL
nordea_analytics-1.22.5.dist-info/top_level.txt
nordea_analytics-1.22.5.dist-info/RECORD
