Metadata-Version: 2.4
Name: nordea-analytics
Version: 1.22.5
Summary: Nordea Analytics Python library
Home-page: https://github.com/NordeaOSS/nordea-analytics
Author: Nordea Desk Quants and Markets Advisory Tools
Author-email: E-advisorySupport@nordea.com
Classifier: Programming Language :: Python :: 3
Classifier: Programming Language :: Python :: 3 :: Only
Classifier: Programming Language :: Python :: 3.9
Classifier: Programming Language :: Python :: 3.11
Classifier: Programming Language :: Python :: 3.12
Classifier: License :: OSI Approved :: GNU General Public License v3 (GPLv3)
Classifier: Operating System :: Microsoft :: Windows
Requires-Python: >=3.9
License-File: LICENCE.md
Requires-Dist: pandas<3,>=2
Requires-Dist: requests<3,>=2.20
Requires-Dist: pyaml>=16.12.0
Requires-Dist: pip_system_certs
Dynamic: license-file
